{"chunk_definitions":[{"chunk_id":"csetup_chunk","chunk_label":"setup","document_id":"76AFA2C","expansion_state":0,"options":{"engine":"r","include":false,"label":"setup"},"row":9,"row_count":1,"visible":true},{"chunk_id":"czwwqw0k35szu","chunk_label":"cars","document_id":"76AFA2C","expansion_state":0,"options":{"engine":"r","label":"cars"},"row":19,"row_count":1,"visible":true},{"chunk_id":"cluvkufxc40u4","chunk_label":"pressure","document_id":"76AFA2C","expansion_state":0,"options":{"echo":false,"engine":"r","label":"pressure"},"row":27,"row_count":1,"visible":true},{"chunk_id":"cqjs8azqo3hrh","chunk_label":"unnamed-chunk-1","document_id":"76AFA2C","expansion_state":0,"options":{},"row":32,"row_count":1,"visible":true}],"default_chunk_options":{"echo":true},"doc_write_time":1585309415,"working_dir":null}